<translation>
	<sentence key="DATAVIEW">
		<translation language="fr">Visualisation de données</translation>
		<translation language="en">Data view</translation>
	</sentence>
	
	<sentence key="DATAVIEW_DETAILS">
		<translation language="fr">L'application de consultation de données permet de mettre à disposition une base de données de manière sécurisée, en limitant l'accès aux informations privées aux seuls détenteurs d'un compte sur l'Intranet.</translation>
		<translation language="en">The data view application has been designed to provide a secured way of publishing data for the Intranet's users.</translation>
	</sentence>
	
	<sentence key="DV_TO">
		<translation language="fr">à</translation>
		<translation language="en">to</translation>
	</sentence>
	
	<sentence key="DV_RECORDS">
		<translation language="fr">enregistrements</translation>
		<translation language="en">records</translation>
	</sentence>
	
	<sentence key="DV_PREVIOUS">
		<translation language="fr">Précédent</translation>
		<translation language="en">Previous</translation>
	</sentence>
	
	<sentence key="DV_NEXT">
		<translation language="fr">Suivant</translation>
		<translation language="en">Next</translation>
	</sentence>
	
	<sentence key="DV_VIEWINGRECORDS">
		<translation language="fr">Visualisation des enregistrements</translation>
		<translation language="en">Viewing records</translation>
	</sentence>
	
	<sentence key="DV_DETAILS">
		<translation language="fr">Détails</translation>
		<translation language="en">Details</translation>
	</sentence>
	
	<sentence key="DV_DISPLAYDETAILS">
		<translation language="fr">Afficher plus de détails sur cet enregistrement</translation>
		<translation language="en">Display more details about this record</translation>
	</sentence>
	
	<sentence key="DV_BACKTOLISTING">
		<translation language="fr">Retour à la liste</translation>
		<translation language="en">Back to list</translation>
	</sentence>

	<sentence key="DV_LIST">
		<translation language="fr">Liste</translation>
		<translation language="en">List</translation>
	</sentence>

	<sentence key="DV_RESULT">
		<translation language="fr">résultat</translation>
		<translation language="en">result</translation>
	</sentence>

	<sentence key="DV_RESULTS">
		<translation language="fr">résultats</translation>
		<translation language="en">results</translation>
	</sentence>
	
	<sentence key="DV_FORSEARCHKEYWORD">
		<translation language="fr">pour le mot clé</translation>
		<translation language="en">for keyword</translation>
	</sentence>	
	
	<sentence key="DV_SEARCH">
		<translation language="fr">Recherche</translation>
		<translation language="en">Search</translation>
	</sentence>

	<sentence key="DV_NOSEARCHRESULTSFOR">
		<translation language="fr">Aucun résultat pour le mot clé</translation>
		<translation language="en">No result for keyword</translation>
	</sentence>
	
	<sentence key="DATAVIEW_DEFAULT">
		<translation language="fr">L'application de consultation de données vous permet d'accéder aux données stockées dans les diverses bases de données mises à disposition</translation>
		<translation language="en">The data view application has been designed in order to give you access to data stored in database</translation>
	</sentence>
</translation>